pyasset/__init__.py
pyasset/builder_decorator.py
pyasset/percentage/__init__.py
pyasset/percentage/bar.py
pyasset/percentage/captions.py
pyasset/percentage/percentage.py
pyasset-1.0.1.dist-info/LICENSE
pyasset-1.0.1.dist-info/METADATA
pyasset-1.0.1.dist-info/WHEEL
pyasset-1.0.1.dist-info/top_level.txt
pyasset-1.0.1.dist-info/RECORD
