Metadata-Version: 2.1
Name: pyasset
Version: 1.0.1
Summary: Python Asset Library.
Home-page: 
Author: minwoo lee
Author-email: dlalsdn1009@naver.com
Classifier: Programming Language :: Python :: 3
Classifier: License :: OSI Approved :: MIT License
Classifier: Operating System :: OS Independent
Requires-Python: >=3.6
License-File: LICENSE
